latent_space_builder/__init__.py
latent_space_builder-0.0.1.dist-info/METADATA
latent_space_builder-0.0.1.dist-info/WHEEL
latent_space_builder-0.0.1.dist-info/top_level.txt
latent_space_builder-0.0.1.dist-info/RECORD
