Metadata-Version: 2.1
Name: latent-space-builder
Version: 0.0.1
Summary: A tool for building latent spaces.
Home-page: https://github.com/compSPI/LatentSpaceBuilder
Author: Deeban Ramalingam
Author-email: rdeeban@gmail.com
License: UNKNOWN
Platform: UNKNOWN
Classifier: Programming Language :: Python :: 3
Classifier: License :: OSI Approved :: MIT License
Classifier: Operating System :: OS Independent
Requires-Python: >=3.7
Requires-Dist: jupyterlab
Requires-Dist: scikit-learn
Requires-Dist: h5py
Requires-Dist: numpy
Requires-Dist: pyDiffMap
Requires-Dist: setuptools
